example_package/RichTest.py
example_package/__init__.py
example_package/example.py
example_package/pyecharts_test.py
example_package/reportlab_pdf.py
rolling_king/__init__.py
rolling_king/jason/__init__.py
rolling_king/jason/autogen/__init__.py
rolling_king/jason/autogen/auto_generate.py
rolling_king/jason/chatgpt/__init__.py
rolling_king/jason/chatgpt/openai.py
rolling_king/jason/newcore/__init__.py
rolling_king/jason/newcore/test_ccc.py
rolling_king/jason/openpyxl/__init__.py
rolling_king/jason/openpyxl/excel_util.py
rolling_king/jason/playwright/__init__.py
rolling_king/jason/playwright/playwright_common.py
rolling_king/jason/playwright/test_generate.py
rolling_king/jason/playwright/test_playwright.py
rolling_king/jason/pypac/__init__.py
rolling_king/jason/pypac/pyfile1.py
rolling_king/jason/pypac/pyfile2.py
rolling_king/jason/pypac/test.py
rolling_king/jason/pytest/__init__.py
rolling_king/jason/pytest/conftest.py
rolling_king/jason/pytest/test_class.py
rolling_king/jason/pytest/test_sample.py
rolling_king/jason/python/ClassTest.py
rolling_king/jason/python/DbTest.py
rolling_king/jason/python/MailTest.py
rolling_king/jason/python/MyPyTest.py
rolling_king/jason/python/PythonTest.py
rolling_king/jason/python/QueueTest.py
rolling_king/jason/python/SeniorTest.py
rolling_king/jason/python/__init__.py
rolling_king/jason/python/socket/SocketClient.py
rolling_king/jason/python/socket/SocketServer.py
rolling_king/jason/python/socket/__init__.py
rolling_king/jason/python/thread/ThreadingTest.py
rolling_king/jason/python/thread/_ThreadTest.py
rolling_king/jason/python/thread/__init__.py
rolling_king/jason/python/tools/ExcelTest.py
rolling_king/jason/python/tools/__init__.py
rolling_king/jason/python/tools/xmind_excel_converter.py
rolling_king/jason/python/tools/zy_schedule.py
rolling_king/jason/python/tools/zy_shell.py
rolling_king/jason/python/tools/zy_stamp_tool.py
rolling_king/jason/requests/__init__.py
rolling_king/jason/requests/http_sender_module.py
rolling_in_the_deep-0.1.3.dist-info/LICENSE
rolling_in_the_deep-0.1.3.dist-info/METADATA
rolling_in_the_deep-0.1.3.dist-info/WHEEL
rolling_in_the_deep-0.1.3.dist-info/top_level.txt
rolling_in_the_deep-0.1.3.dist-info/RECORD
